tailer_sdk/__init__.py
tailer_sdk/sql_dag_generator.py
tailer_sdk/tailer_auth.py
tailer_sdk/tailer_config.py
tailer_sdk/tailer_configuration_manager.py
tailer_sdk/tailer_crypto.py
tailer_sdk/tailer_gcp_cf_manager.py
tailer_sdk/tailer_help.py
tailer_sdk/tailer_misc.py
tailer_sdk/tailersdk.py
tailer_sdk/tailer_sdk_templates/__init__.py
tailer_sdk/tailer_sdk_templates/template_dag.py
tailer_sdk/tailer_sdk_templates/template_main.py
tailer_sdk-1.3.19.dist-info/LICENSE
tailer_sdk-1.3.19.dist-info/METADATA
tailer_sdk-1.3.19.dist-info/WHEEL
tailer_sdk-1.3.19.dist-info/entry_points.txt
tailer_sdk-1.3.19.dist-info/top_level.txt
tailer_sdk-1.3.19.dist-info/RECORD
